notes50/notes50.py
notes50-0.0.5.dist-info/LICENSE
notes50-0.0.5.dist-info/METADATA
notes50-0.0.5.dist-info/WHEEL
notes50-0.0.5.dist-info/entry_points.txt
notes50-0.0.5.dist-info/top_level.txt
notes50-0.0.5.dist-info/RECORD
