Metadata-Version: 2.1
Name: notes50
Version: 0.0.5
Summary: CS50 Notes And Psets Reader
Author-email: Zed <zeeshantechnical9128@gmail.com>
License: The GPLv3 License (GPLv3)        
Keywords: CS50,CS50P,Notes,Psets
Classifier: Programming Language :: Python :: 3
Classifier: License :: OSI Approved :: GNU General Public License v3 (GPLv3)
Classifier: Operating System :: OS Independent
Requires-Python: >=3.7
License-File: LICENSE
Requires-Dist: appdirs (==1.4.4)
Requires-Dist: beautifulsoup4 (==4.11.1)
Requires-Dist: bs4 (==0.0.1)
Requires-Dist: commonmark (==0.9.1)
Requires-Dist: joblib (==1.1.0)
Requires-Dist: lxml (==4.9.1)
Requires-Dist: markdownify (==0.11.6)
Requires-Dist: Pygments (==2.13.0)
Requires-Dist: rich (==12.5.1)
Requires-Dist: six (==1.16.0)
Requires-Dist: soupsieve (==2.3.2.post1)
